{
  "menu": {
    "type": "object",
    "properties": {},
    "id": "menu"
  },
  "login": {
    "type": "object",
    "comment": "Login",
    "properties": {
      "username": {
        "type": "string",
        "label": "username"
      },
      "password": {
        "type": "string",
        "label": "password"
      },
      "submit": {
        "type": "action",
        "parameters": {
          "username": {
            "type": "string"
          },
          "password": {
            "type": "string"
          }
        }
      },
      "errorMessage": {
        "type": "string",
        "update": {
          "type": "none"
        }
      }
    },
    "id": "login"
  },
  "categorylistview": {
    "type": "object",
    "comment": "Blank",
    "properties": {
      "Group": {
        "type": "array",
        "items": {
          "type": "object",
          "properties": {
            "Title": {
              "type": "string",
              "update": {
                "type": "none"
              }
            },
            "Description": {
              "type": "string",
              "update": {
                "type": "none"
              }
            },
            "icon": {
              "type": "string"
            },
            "viewDetails": {
              "type": "action"
            }
          }
        },
        "update": {
          "type": "none"
        }
      }
    },
    "id": "categorylistview"
  }
}